{
  "number": "0310",
  "idioms": [
    "turn over (~)"
  ],
  "means": [
    {
      "idiom-jp": "〜を引き渡す；〜を譲る",
      "example-sentence": "According to a TV newscast, another badly abused child was turned over to an institution.",
      "sentence-jp": "テレビのニュース放送によれば、ひどい虐待を受けた子供がまた1人、施設に引き渡された。"
    },
    {
      "idiom-jp": "〜をひっくり返す；(ページなど)をめくる；ひっくり返る",
      "example-sentence": "Turning the finished letter over and folding it, the secretary put it into an envelope.",
      "sentence-jp": "書き終わった手紙を裏返してたたむと、秘書はそれを封筒に入れた。"
    }
  ],
  "notes": [
    "裏では「ページをめくる」の意味では over を付けないことも多い。",
    "turn over a new leaf は「心機一転やり直す」の意味の口語表現。直訳は「新しいページをめくる」。",
    "①②ともに turn ~ over の語順も可。②は他動詞の場合。"
  ]
}
